Workbook

Sheet Главная
A1: ФИНАНСОВАЯ МОДЕЛЬ ЮНИТ-ЭКОНОМИКИ МАРКЕТПЛЕЙСА
A3: ?? ВХОДНЫЕ ПАРАМЕТРЫ
A4: Параметр | B4: Значение | C4: Ед. изм. | D4: Описание
A5: Бюджет на привлечение | B5: 1000000 | C5: ? | D5: Общий бюджет на маркетинг | E5: КЛЮЧЕВЫЕ ПОКАЗАТЕЛИ
A6: Количество продавцов | B6: 100 | C6: чел | D6: План по привлечению
A7: Средний оборот продавца | B7: 150000 | C7: ?/мес | D7: Выручка продавца в месяц | E7: CAC | G7: LTV
A8: Комиссия площадки | B8: 0.1 | C8: % | D8: Процент от оборота | E8: =B14 -> 10000 | G8: =B15 -> 360000
A9: Средний срок жизни | B9: 24 | C9: мес | D9: Время сотрудничества | E9: стоимость привлечения | G9: пожизненная ценность
A10: Операционные расходы | B10: 0.15 | C10: % | D10: Расходы на обслуживание | E10: ?/продавец | G10: ?
A12: ВЫХОДНЫЕ РЕЗУЛЬТАТЫ | E12: PBP | G12: ROMI
A13: Показатель | B13: Значение | C13: Ед. изм. | E13: =B16 -> 0.66666667 | G13: =B19 -> 35
A14: CAC (стоимость привлечения) | B14: =B5/B6 -> 10000 | C14: ?/продавец | E14: срок окупаемости | G14: возврат инвестиций
A15: LTV (пожизненная ценность) | B15: =(B7*B8)*B9 -> 360000 | C15: ? | E15: месяцев | G15: %
A16: Срок окупаемости (PBP) | B16: =B14/(B7*B8) -> 0.66666667 | C16: мес
A17: Маржа на продавца | B17: =B15-B14 -> 350000 | C17: ?
A18: Общая прибыль | B18: =B17*B6*(1-B10) -> 29750000 | C18: ?
A19: ROMI | B19: =(B15-B14)/B14 -> 35 | C19: %

Sheet Когорты
A1: КОГОРТНЫЙ АНАЛИЗ ДОХОДОВ
A3: Месяц | B3: Оборот | C3: Комиссия | D3: Доход | E3: Накоплено
A4: 1 | B4: =Главная!$B$7 -> 150000 | C4: =Главная!$B$8 -> 0.1 | D4: =B4*C4 -> 15000 | E4: =D4 -> 15000
A5: 2 | B5: =Главная!$B$7 -> 150000 | C5: =Главная!$B$8 -> 0.1 | D5: =B5*C5 -> 15000 | E5: =E4+D5 -> 30000
A6: 3 | B6: =Главная!$B$7 -> 150000 | C6: =Главная!$B$8 -> 0.1 | D6: =B6*C6 -> 15000 | E6: =E5+D6 -> 45000
A7: 4 | B7: =Главная!$B$7 -> 150000 | C7: =Главная!$B$8 -> 0.1 | D7: =B7*C7 -> 15000 | E7: =E6+D7 -> 60000
A8: 5 | B8: =Главная!$B$7 -> 150000 | C8: =Главная!$B$8 -> 0.1 | D8: =B8*C8 -> 15000 | E8: =E7+D8 -> 75000
A9: 6 | B9: =Главная!$B$7 -> 150000 | C9: =Главная!$B$8 -> 0.1 | D9: =B9*C9 -> 15000 | E9: =E8+D9 -> 90000
A10: 7 | B10: =Главная!$B$7 -> 150000 | C10: =Главная!$B$8 -> 0.1 | D10: =B10*C10 -> 15000 | E10: =E9+D10 -> 105000
A11: 8 | B11: =Главная!$B$7 -> 150000 | C11: =Главная!$B$8 -> 0.1 | D11: =B11*C11 -> 15000 | E11: =E10+D11 -> 120000
A12: 9 | B12: =Главная!$B$7 -> 150000 | C12: =Главная!$B$8 -> 0.1 | D12: =B12*C12 -> 15000 | E12: =E11+D12 -> 135000
A13: 10 | B13: =Главная!$B$7 -> 150000 | C13: =Главная!$B$8 -> 0.1 | D13: =B13*C13 -> 15000 | E13: =E12+D13 -> 150000
A14: 11 | B14: =Главная!$B$7 -> 150000 | C14: =Главная!$B$8 -> 0.1 | D14: =B14*C14 -> 15000 | E14: =E13+D14 -> 165000
A15: 12 | B15: =Главная!$B$7 -> 150000 | C15: =Главная!$B$8 -> 0.1 | D15: =B15*C15 -> 15000 | E15: =E14+D15 -> 180000
A16: 13 | B16: =Главная!$B$7 -> 150000 | C16: =Главная!$B$8 -> 0.1 | D16: =B16*C16 -> 15000 | E16: =E15+D16 -> 195000
... A27: 24 | B27: =Главная!$B$7 -> 150000 | C27: =Главная!$B$8 -> 0.1 | D27: =B27*C27 -> 15000 | E27: =E26+D27 -> 360000

Sheet Сценарии
A1: СРАВНЕНИЕ СЦЕНАРИЕВ
A3: Параметр | B3: Базовый | C3: Агрессивный | D3: Премиум | E3: Дискаунтер
A4: CAC | B4: =Главная!B14 -> 10000 | C4: 5000 | D4: 15000 | E4: 2000
A5: LTV | B5: =Главная!B15 -> 360000 | C5: =(Главная!B7*Главная!B8)*36 -> 540000 | D5: =(Главная!B7*1.3*Главная!B8)*36 -> 702000 | E5: =(Главная!B7*0.7*Главная!B8)*12 -> 126000
A6: Окупаемость | B6: =B4/(Главная!B7*Главная!B8) -> 0.66666667 | C6: =C4/(Главная!B7*Главная!B8) -> 0.33333333 | D6: =D4/(Главная!B7*1.3*Главная!B8) -> 0.76923077 | E6: =E4/(Главная!B7*0.7*Главная!B8) -> 0.19047619
A8: ВЫВОД:
A9: =IF(B6<6, "? Агрессивный рост окупается быстро", "?? Требуется оптимизация") -> ? Агрессивный рост окупается быстро
